mkkm_mr/__init__.py
mkkm_mr/lib.py
mkkm_mr-0.2.5.dist-info/LICENSE
mkkm_mr-0.2.5.dist-info/WHEEL
mkkm_mr-0.2.5.dist-info/METADATA
mkkm_mr-0.2.5.dist-info/RECORD
