Metadata-Version: 2.1
Name: mkkm-mr
Version: 0.2.5
Summary: MKKM-MR Python Implementation
Home-page: https://github.com/fmakdemir/mkkm-mr
License: BSD-2-Clause
Author: Fma
Author-email: fmakdemir@users.noreply.github.com
Requires-Python: >=3.6.1,<4.0.0
Classifier: License :: OSI Approved :: BSD License
Classifier: Programming Language :: Python :: 3
Classifier: Programming Language :: Python :: 3.7
Classifier: Programming Language :: Python :: 3.8
Requires-Dist: cvxopt (>=1.2.5,<2.0.0)
Requires-Dist: numpy (>=1.19.1,<2.0.0)
Requires-Dist: scipy (>=1.5.2,<2.0.0)
Project-URL: Repository, https://github.com/fmakdemir/mkkm-mr
